swmmtonetcdf/__init__.py
swmmtonetcdf/__main__.py
swmmtonetcdf/swmmtonetcdf.py
swmmtonetcdf/tests/__init__.py
swmmtonetcdf/tests/test_swmm_output_export.py
swmmtonetcdf/tests/data/__init__.py
swmmtonetcdf-0.1.0.dist-info/LICENSE
swmmtonetcdf-0.1.0.dist-info/METADATA
swmmtonetcdf-0.1.0.dist-info/WHEEL
swmmtonetcdf-0.1.0.dist-info/entry_points.txt
swmmtonetcdf-0.1.0.dist-info/top_level.txt
swmmtonetcdf-0.1.0.dist-info/RECORD
