Metadata-Version: 2.1
Name: swmmtonetcdf
Version: 0.1.0
Summary: A tool to write SWMM output to netcdf
Home-page: https://github.com/cbuahin/swmmtonetcdf
Author: Caleb Buahin, Jennifer Wu
Author-email: caleb.buahin@gmail.com
License: GNU GPLv3
Keywords: swmm5,swmm,hydraulics,hydrology,modeling,collection system
Platform: UNKNOWN
Classifier: Topic :: Scientific/Engineering
Classifier: Operating System :: Microsoft :: Windows
Classifier: Operating System :: Unix
Classifier: Operating System :: MacOS
Classifier: License :: OSI Approved :: BSD License
Classifier: Programming Language :: Python :: 3
Classifier: Programming Language :: Python :: 3.6
Classifier: Programming Language :: Python :: 3.7
Classifier: Programming Language :: Python :: 3.8
Classifier: Programming Language :: Python :: 3.9
Classifier: Programming Language :: Python :: 3.10
Classifier: Development Status :: 4 - Beta
Requires-Python: >=3.6
Requires-Dist: six (~=1.16.0)
Requires-Dist: h5py (~=3.1.0)
Requires-Dist: netCDF4 (~=1.5.8)
Requires-Dist: cftime (~=1.4.1)
Requires-Dist: julian (~=0.14)
Requires-Dist: swmm-toolkit (~=0.8.2)
Requires-Dist: numpy (~=1.19.4)
